fastapis/__init__.py
fastapis/common/__init__.py
fastapis/common/_config.py
fastapis/common/loggers.py
fastapis/db/__init__.py
fastapis/db/base.py
fastapis/db/types.py
fastapis/web/__init__.py
fastapis/web/_repository.py
fastapis/web/_router.py
fastapis/web/types.py
fastapis-0.13.dist-info/METADATA
fastapis-0.13.dist-info/WHEEL
fastapis-0.13.dist-info/top_level.txt
fastapis-0.13.dist-info/RECORD
