Metadata-Version: 2.4
Name: fastapis
Version: 0.13
Summary: Simple FastAPI/SQLAlchemy to super easy create (generic) routes, delcare db types and more.
Home-page: https://github.com/ultrafunkamsterdam/fastapis
Author: UltrafunkAmsterdam
Author-email: Me <non@yourbusiness.no>
License: ISC
Project-URL: homepage, https://www.github.com/ultrafunkamsterdam/fastapis
Project-URL: repository, https://github.com/ultrafunkamsterdam/fastapis.git
Project-URL: documentation, https://ultrafunkamsterdam.github.io/fastapis
Project-URL: issues, https://github.com/ultrafunkamsterdam/fastapis/issues
Classifier: Development Status :: 5 - Production/Stable
Classifier: Intended Audience :: Developers
Classifier: Intended Audience :: System Administrators
Classifier: Operating System :: POSIX
Classifier: Operating System :: Microsoft :: Windows
Classifier: Programming Language :: Python
Classifier: Topic :: Software Development :: Libraries :: Python Modules
Requires-Python: >=3.9
Requires-Dist: aiomysql==0.2.0
Requires-Dist: aiosqlite==0.21.0
Requires-Dist: annotated-types==0.7.0
Requires-Dist: anyio==4.9.0
Requires-Dist: asyncpg==0.30.0
Requires-Dist: click==8.2.1
Requires-Dist: colorama==0.4.6
Requires-Dist: fastapi==0.115.12
Requires-Dist: greenlet==3.2.2
Requires-Dist: h11==0.16.0
Requires-Dist: idna==3.10
Requires-Dist: itsdangerous==2.2.0
Requires-Dist: pydantic==2.11.5
Requires-Dist: pydantic_core==2.33.2
Requires-Dist: PyMySQL==1.1.1
Requires-Dist: python-multipart==0.0.20
Requires-Dist: PyYAML==6.0.2
Requires-Dist: sniffio==1.3.1
Requires-Dist: SQLAlchemy==2.0.41
Requires-Dist: starlette==0.46.2
Requires-Dist: typing-inspection==0.4.1
Requires-Dist: typing_extensions==4.13.2
Requires-Dist: uvicorn==0.34.2
Provides-Extra: dev
Requires-Dist: black>=23.1.0; extra == "dev"
Requires-Dist: twine>=4.0.0; extra == "dev"
Requires-Dist: build; extra == "dev"
Dynamic: author
Dynamic: home-page
